{
	"nodes": [
		{ "country": "East Timor", "code": "tl" },
		{ "country": "Canada", "code": "ca" },
		{ "country": "Turkmenistan", "code": "tm" },
		{ "country": "United States of America", "code": "us" },
		{ "country": "Lithuania", "code": "lt" },
		{ "country": "Cambodia", "code": "kh" },
		{ "country": "Ethiopia", "code": "et" },
		{ "country": "Swaziland", "code": "sz" },
		{ "country": "Argentina", "code": "ar" },
		{ "country": "Bolivia", "code": "bo" },
		{ "country": "Cameroon", "code": "cm" },
		{ "country": "Burkina Faso", "code": "bf" },
		{ "country": "Ghana", "code": "gh" },
		{ "country": "Saudi Arabia", "code": "sa" },
		{ "country": "Slovenia", "code": "si" },
		{ "country": "Guatemala", "code": "gt" },
		{ "country": "Bosnia and Herzegovina", "code": "ba" },
		{ "country": "Kuwait", "code": "kw" },
		{ "country": "Russian Federation", "code": "ru" },
		{ "country": "Jordan", "code": "jo" },
		{ "country": "St. Lucia", "code": "lc" },
		{ "country": "Spain", "code": "es" },
		{ "country": "Liberia", "code": "lr" },
		{ "country": "Netherlands", "code": "nl" },
		{ "country": "Paraguay", "code": "py" },
		{ "country": "Oman", "code": "om" },
		{ "country": "Tanzania", "code": "tz" },
		{ "country": "Gabon", "code": "ga" },
		{ "country": "Monaco", "code": "mc" },
		{ "country": "Yemen", "code": "ye" },
		{ "country": "Pakistan", "code": "pk" },
		{ "country": "Albania", "code": "al" },
		{ "country": "United Arab Emirates", "code": "ae" },
		{ "country": "India", "code": "in" },
		{ "country": "Azerbaijan", "code": "az" },
		{ "country": "Lesotho", "code": "ls" },
		{ "country": "Kenya", "code": "ke" },
		{ "country": "South Korea", "code": "kr" },
		{ "country": "Tajikistan", "code": "tj" },
		{ "country": "Turkey", "code": "tr" },
		{ "country": "Afghanistan", "code": "af" },
		{ "country": "Bangladesh", "code": "bd" },
		{ "country": "Mauritania", "code": "mr" },
		{ "country": "Solomon Islands", "code": "sb" },
		{ "country": "San Marino", "code": "sm" },
		{ "country": "Kyrgyzstan", "code": "kg" },
		{ "country": "Mongolia", "code": "mn" },
		{ "country": "France", "code": "fr" },
		{ "country": "Rwanda", "code": "rw" },
		{ "country": "Slovakia", "code": "sk" },
		{ "country": "Somalia", "code": "so" },
		{ "country": "Peru", "code": "pe" },
		{ "country": "Laos", "code": "la" },
		{ "country": "Norway", "code": "no" },
		{ "country": "Malawi", "code": "mw" },
		{ "country": "Benin", "code": "bj" },
		{ "country": "Singapore", "code": "sg" },
		{ "country": "Montenegro", "code": "me" },
		{ "country": "Togo", "code": "tg" },
		{ "country": "China", "code": "cn" },
		{ "country": "Armenia", "code": "am" },
		{ "country": "Dominican Republic", "code": "do" },
		{ "country": "Ukraine", "code": "ua" },
		{ "country": "Bahrain", "code": "bh" },
		{ "country": "Finland", "code": "fi" },
		{ "country": "Libya", "code": "ly" },
		{ "country": "Indonesia", "code": "id" },
		{ "country": "Central African Republic", "code": "cf" },
		{ "country": "Sweden", "code": "se" },
		{ "country": "Vietnam", "code": "vn" },
		{ "country": "Mali", "code": "ml" },
		{ "country": "Bulgaria", "code": "bg" },
		{ "country": "Romania", "code": "ro" },
		{ "country": "Angola", "code": "ao" },
		{ "country": "Chad", "code": "td" },
		{ "country": "South Africa", "code": "za" },
		{ "country": "St. Vincent and the Grenadines", "code": "vc" },
		{ "country": "Nicaragua", "code": "ni" },
		{ "country": "Liechtenstein", "code": "li" },
		{ "country": "Antigua & Barbuda", "code": "ag" },
		{ "country": "Malaysia", "code": "my" },
		{ "country": "Senegal", "code": "sn" },
		{ "country": "Mozambique", "code": "mz" },
		{ "country": "Uganda", "code": "ug" },
		{ "country": "Japan", "code": "jp" },
		{ "country": "Niger", "code": "ne" },
		{ "country": "Brazil", "code": "br" },
		{ "country": "Guinea", "code": "gn" },
		{ "country": "Panama", "code": "pa" },
		{ "country": "Guyana", "code": "gy" },
		{ "country": "Costa Rica", "code": "cr" },
		{ "country": "Luxembourg", "code": "lu" },
		{ "country": "Andorra", "code": "ad" },
		{ "country": "Ivory Coast", "code": "ci" },
		{ "country": "Syria", "code": "sy" },
		{ "country": "Nigeria", "code": "ng" },
		{ "country": "Ecuador", "code": "ec" },
		{ "country": "Czech Republic", "code": "cz" },
		{ "country": "Brunei", "code": "bn" },
		{ "country": "Australia", "code": "au" },
		{ "country": "Iran",